lab_student_survey/__init__.py
lab_student_survey/__main__.py
lab_student_survey/analyze.py
lab_student_survey/cli.py
lab_student_survey/gdrive.py
lab_student_survey/main.py
lab_student_survey/py.typed
lab_student_survey-0.4.27.dist-info/LICENSE
lab_student_survey-0.4.27.dist-info/METADATA
lab_student_survey-0.4.27.dist-info/WHEEL
lab_student_survey-0.4.27.dist-info/entry_points.txt
lab_student_survey-0.4.27.dist-info/RECORD
