Metadata-Version: 2.1
Name: lab-student-survey
Version: 0.4.27
Summary: Python package for lab student survey
Home-page: https://github.com/34j/lab-student-survey
License: MIT
Author: 34j
Author-email: 34j.95a2p@simplelogin.com
Requires-Python: >=3.9,<3.13
Classifier: Development Status :: 2 - Pre-Alpha
Classifier: Intended Audience :: Developers
Classifier: License :: OSI Approved :: MIT License
Classifier: Natural Language :: English
Classifier: Operating System :: OS Independent
Classifier: Programming Language :: Python :: 3
Classifier: Programming Language :: Python :: 3.9
Classifier: Programming Language :: Python :: 3.10
Classifier: Programming Language :: Python :: 3.11
Classifier: Programming Language :: Python :: 3.12
Classifier: Topic :: Software Development :: Libraries
Requires-Dist: click (>=8.1.7,<9.0.0)
Requires-Dist: japanize-matplotlib (>=1.1.3,<2.0.0)
Requires-Dist: matplotx (>=0.3.10,<0.4.0)
Requires-Dist: numpy (>=1.26.0,<2.0.0)
Requires-Dist: pandas (>=2.1.0,<3.0.0)
Requires-Dist: pdfkit (>=1.0.0,<2.0.0)
Requires-Dist: pingouin (>=0.5.3,<0.6.0)
Requires-Dist: pydrive2 (>=1.17.0,<2.0.0)
Requires-Dist: tqdm (>=4.66.1,<5.0.0)
Requires-Dist: xhtml2pdf (>=0.2.11,<0.3.0)
Project-URL: Bug Tracker, https://github.com/34j/lab-student-survey/issues
Project-URL: Changelog, https://github.com/34j/lab-student-survey/blob/main/CHANGELOG.md
Project-URL: Documentation, https://lab-student-survey.readthedocs.io
Project-URL: Repository, https://github.com/34j/lab-student-survey
